secrets_helper/__init__.py
secrets_helper/_commands.py
secrets_helper/identifiers.py
secrets_helper/_util/__init__.py
secrets_helper/_util/config.py
secrets_helper/_util/execute.py
secrets_helper/_util/secrets.py
secrets_helper-0.1.0.data/data/CHANGELOG.rst
secrets_helper-0.1.0.data/data/LICENSE
secrets_helper-0.1.0.data/data/README.rst
secrets_helper-0.1.0.data/data/requirements.txt
secrets_helper-0.1.0.dist-info/LICENSE
secrets_helper-0.1.0.dist-info/METADATA
secrets_helper-0.1.0.dist-info/WHEEL
secrets_helper-0.1.0.dist-info/entry_points.txt
secrets_helper-0.1.0.dist-info/top_level.txt
secrets_helper-0.1.0.dist-info/RECORD
