Metadata-Version: 2.1
Name: secrets-helper
Version: 0.1.0
Summary: secrets-helper
Home-page: https://github.com/awslabs/secrets-helper
Author: Amazon Web Services
Author-email: aws-cryptools@amazon.com
Maintainer: Amazon Web Services
License: Apache 2.0
Keywords: secrets-helper secrets_helper aws
Platform: UNKNOWN
Classifier: Development Status :: 4 - Beta
Classifier: Intended Audience :: Developers
Classifier: Natural Language :: English
Classifier: License :: OSI Approved :: Apache Software License
Classifier: Programming Language :: Python
Classifier: Programming Language :: Python :: 3
Classifier: Programming Language :: Python :: 3.7
Classifier: Programming Language :: Python :: 3.8
Classifier: Programming Language :: Python :: Implementation :: CPython
Classifier: Topic :: Security
Classifier: Topic :: Security :: Cryptography
Requires-Python: >=3.7
Requires-Dist: click (>=3.0)
Requires-Dist: boto3
